{
    "type": "slice",
    "size": [3072, 3072],
    "alpha": false,
    "slices": [
        {
            "path": "Tex_1903_0.png",
            "rect": [512, 0, 1024, 1024]
        },
        {
            "path": "Tex_1947_0.png",
            "rect": [1536, 0, 1024, 1024]
        },
        {
            "path": "Tex_2013_0.png",
            "rect": [2560, 0, 1024, 1024]
        },
        {
            "path": "Tex_1969_0.png",
            "rect": [0, 1024, 1024, 1024]
        },
        {
            "path": "Tex_1991_0.png",
            "rect": [1024, 1024, 1024, 1024]
        },
        {
            "path": "Tex_1925_0.png",
            "rect": [2048, 1024, 1024, 1024]
        },
        {
            "path": "Tex_2079_0.png",
            "rect": [512, 2048, 1024, 1024]
        },
        {
            "path": "Tex_2057_0.png",
            "rect": [1536, 2048, 1024, 1024]
        }
    ]
}